desktop_app/__init__.py
desktop_app/__main__.py
desktop_app/__version__.py
desktop_app/environment.py
desktop_app/fix_entry_points.py
desktop_app/launcher.py
desktop_app/linux.py
desktop_app/shell.py
desktop_app/windows.py
desktop_app/wineventhook.cpython-37m-darwin.so
desktop_app-0.4.1.dist-info/LICENSE
desktop_app-0.4.1.dist-info/METADATA
desktop_app-0.4.1.dist-info/WHEEL
desktop_app-0.4.1.dist-info/entry_points.txt
desktop_app-0.4.1.dist-info/top_level.txt
desktop_app-0.4.1.dist-info/RECORD
