Metadata-Version: 2.1
Name: desktop-app
Version: 0.4.1
Summary: OS menu shortcuts, correct taskbar behaviour, and environment activation for Python GUI apps
Home-page: http://github.com/chrisjbillington/desktop-app
Author: Chris Billington
Author-email: chrisjbillington@gmail.com
License: BSD
Keywords: desktop windows launchers taskbar start-menu
Classifier: License :: OSI Approved :: BSD License
Classifier: Programming Language :: Python :: 3 :: Only
Classifier: Programming Language :: Python :: 3.7
Classifier: Programming Language :: Python :: 3.8
Classifier: Programming Language :: Python :: 3.9
Classifier: Programming Language :: Python :: 3.10
Requires-Python: >=3.6
License-File: LICENSE
Requires-Dist: setuptools-scm
Requires-Dist: importlib-metadata
Requires-Dist: distlib
Requires-Dist: pywin32 ; sys_platform == "win32"
